{
  "type": "minecraft:block",
  "pools": [
    {
      "rolls": 1,
      "entries": [
        {
          "type": "minecraft:item",
          "name": "uniquecrops:book_discount"
        }
      ],
      "conditions": [
        {
          "condition": "minecraft:block_state_property",
          "block": "uniquecrops:crop_knowledge",
          "properties": {
            "age": "7"
          }
        }
      ]
    },
    {
      "rolls": 1,
      "entries": [
        {
          "type": "minecraft:item",
          "name": "uniquecrops:seedknowledge"
        }
      ],
      "conditions": [
        {
          "condition": "minecraft:survives_explosion"
        }
      ]
    }
  ]
}